aidebug/__init__.py
aidebug/aidebug.py
aidebug/core/__init__.py
aidebug/core/clientv2/__init__.py
aidebug/core/clientv2/clientv2.py
aidebug/core/gui/__init__.py
aidebug/core/gui/select_dirs.py
aidebug/core/utils/__init__.py
aidebug/core/utils/error_handler.py
aidebug/core/utils/files_data.py
aidebug/core/utils/timer.py
aidebug-0.1.6.dist-info/LICENSE
aidebug-0.1.6.dist-info/METADATA
aidebug-0.1.6.dist-info/WHEEL
aidebug-0.1.6.dist-info/entry_points.txt
aidebug-0.1.6.dist-info/top_level.txt
aidebug-0.1.6.dist-info/RECORD
