Metadata-Version: 2.1
Name: aidebug
Version: 0.1.6
Summary: AI Coding Assistant Shell
Author: 00-Python (Joseph Webster)
Author-email: <rwc.webster@gmail.com>
Keywords: aidebug,ai debug,ai debugging,debug with AI,Code with ai,ai programming,python,AI,Coding Assistant,AI Coding,OpenAI,GPT-4,GPT
Classifier: Intended Audience :: Developers
Classifier: Programming Language :: Python :: 3
Classifier: Operating System :: Unix
Classifier: Operating System :: Microsoft :: Windows
License-File: LICENSE
Requires-Dist: PyQt5
Requires-Dist: colorama
Requires-Dist: requests
Requires-Dist: urllib3
Requires-Dist: idna
Requires-Dist: prompt-toolkit
Requires-Dist: pygments
Requires-Dist: pyreadline
